django_genfkadmin-0.1.4.dist-info/licenses/LICENSE
genfkadmin/__init__.py
genfkadmin/admin.py
genfkadmin/fields.py
genfkadmin/forms.py
django_genfkadmin-0.1.4.dist-info/METADATA
django_genfkadmin-0.1.4.dist-info/WHEEL
django_genfkadmin-0.1.4.dist-info/top_level.txt
django_genfkadmin-0.1.4.dist-info/RECORD
