Metadata-Version: 2.4
Name: django-genfkadmin
Version: 0.1.4
Summary: No frills GenericForeignKeys for your Django Admin
Author-email: Michael Spallino <mikehspallino@gmail.com>
Maintainer-email: Michael Spallino <mikehspallino@gmail.com>
Project-URL: Homepage, https://github.com/mikespallino/django-genericfkadmin
Project-URL: Issues, https://github.com/mikespallino/django-genericfkadmin/issues
Classifier: Development Status :: 2 - Pre-Alpha
Classifier: Intended Audience :: Developers
Classifier: Topic :: Software Development :: Libraries
Classifier: Topic :: Software Development :: Libraries :: Application Frameworks
Classifier: License :: OSI Approved :: MIT License
Classifier: Framework :: Django :: 4.2
Classifier: Framework :: Django :: 5
Classifier: Framework :: Django :: 5.1
Classifier: Framework :: Django :: 5.2
Classifier: Programming Language :: Python
Classifier: Programming Language :: Python :: 3.10
Classifier: Programming Language :: Python :: 3.11
Classifier: Programming Language :: Python :: 3.12
Classifier: Programming Language :: Python :: 3.13
Classifier: Operating System :: OS Independent
Requires-Python: <3.14,>=3.10
License-File: LICENSE
Requires-Dist: django>=4.2
Dynamic: license-file
